acda/__init__.py
acda/__main__.py
acda/_version.py
acda/general_functions.py
acda/method_functions.py
acda/plot_functions.py
acda/__pycache__/__init__.cpython-38.pyc
acda/__pycache__/_version.cpython-38.pyc
acda/__pycache__/general_functions.cpython-38.pyc
acda/__pycache__/method_functions.cpython-38.pyc
acda/__pycache__/plot_functions.cpython-38.pyc
acda-0.0.6.dist-info/LICENSE
acda-0.0.6.dist-info/METADATA
acda-0.0.6.dist-info/WHEEL
acda-0.0.6.dist-info/top_level.txt
acda-0.0.6.dist-info/RECORD
