Metadata-Version: 2.1
Name: acda
Version: 0.0.6
Summary: Implementation of drug synergy prediction algorithms
Home-page: https://github.com/TheJacksonLaboratory/drug-synergy
Author: S. Domanskyi, A. Srivastava
Author-email: sergii.domanskyi@jax.org
License: MIT License
Platform: UNKNOWN
Classifier: License :: OSI Approved :: MIT License
Classifier: Programming Language :: Python :: 3
Classifier: Topic :: Scientific/Engineering :: Bio-Informatics
Classifier: Intended Audience :: Science/Research
Classifier: Intended Audience :: Education
Classifier: Intended Audience :: Developers
Classifier: Intended Audience :: End Users/Desktop
Classifier: Operating System :: MacOS
Classifier: Operating System :: Microsoft :: Windows
Classifier: Operating System :: Unix
Classifier: Topic :: Education
Classifier: Topic :: Utilities
Requires-Python: >=3.8
License-File: LICENSE
Requires-Dist: numpy (>=1.19.1)
Requires-Dist: pandas (>=1.0.1)
Requires-Dist: scipy (>=1.4.1)
Requires-Dist: matplotlib (>=3.1.3)
Requires-Dist: scikit-learn (>=0.22.1)
